MANIFEST.in
setup.cfg
setup.py
beyondskins/__init__.py
beyondskins.pythonbrasil.site.egg-info/PKG-INFO
beyondskins.pythonbrasil.site.egg-info/SOURCES.txt
beyondskins.pythonbrasil.site.egg-info/dependency_links.txt
beyondskins.pythonbrasil.site.egg-info/entry_points.txt
beyondskins.pythonbrasil.site.egg-info/namespace_packages.txt
beyondskins.pythonbrasil.site.egg-info/not-zip-safe
beyondskins.pythonbrasil.site.egg-info/requires.txt
beyondskins.pythonbrasil.site.egg-info/top_level.txt
beyondskins/pythonbrasil/__init__.py
beyondskins/pythonbrasil/site/README.txt
beyondskins/pythonbrasil/site/__init__.py
beyondskins/pythonbrasil/site/configure.zcml
beyondskins/pythonbrasil/site/profiles.zcml
beyondskins/pythonbrasil/site/quickinstaller.py
beyondskins/pythonbrasil/site/setuphandlers.py
beyondskins/pythonbrasil/site/skins.zcml
beyondskins/pythonbrasil/site/tests.py
beyondskins/pythonbrasil/site/version.txt
beyondskins/pythonbrasil/site/browser/__init__.py
beyondskins/pythonbrasil/site/browser/configure.zcml
beyondskins/pythonbrasil/site/browser/interfaces.py
beyondskins/pythonbrasil/site/browser/viewlets.py
beyondskins/pythonbrasil/site/browser/images/README.txt
beyondskins/pythonbrasil/site/browser/stylesheets/README.txt
beyondskins/pythonbrasil/site/browser/templates/colophon.pt
beyondskins/pythonbrasil/site/browser/templates/footer.pt
beyondskins/pythonbrasil/site/browser/templates/logo.pt
beyondskins/pythonbrasil/site/browser/templates/viewlet.pt
beyondskins/pythonbrasil/site/doc/__init__.py
beyondskins/pythonbrasil/site/doc/browser.txt
beyondskins/pythonbrasil/site/profiles/default/beyondskins.site_various.txt
beyondskins/pythonbrasil/site/profiles/default/cssregistry.xml
beyondskins/pythonbrasil/site/profiles/default/import_steps.xml
beyondskins/pythonbrasil/site/profiles/default/jsregistry.xml
beyondskins/pythonbrasil/site/profiles/default/metadata.xml
beyondskins/pythonbrasil/site/profiles/default/skins.xml
beyondskins/pythonbrasil/site/profiles/default/viewlets.xml
beyondskins/pythonbrasil/site/profiles/to300/cssregistry.xml
beyondskins/pythonbrasil/site/profiles/to300/skins.xml
beyondskins/pythonbrasil/site/profiles/to300/viewlets.xml
beyondskins/pythonbrasil/site/skins/beyondskins_pythonbrasil_site_images/CONTENT.txt
beyondskins/pythonbrasil/site/skins/beyondskins_pythonbrasil_site_images/blank.gif
beyondskins/pythonbrasil/site/skins/beyondskins_pythonbrasil_site_images/close.gif
