Metadata-Version: 1.0
Name: beyondskins.pythonbrasil.site
Version: 3.0.0
Summary: This product is a installable Plone 3 Theme developed by Simples Consultoria for use in Python Brasil [7] Conference web site.
Home-page: http://www.simplesconsultoria.com.br/
Author: Simples Consultoria
Author-email: contato@simplesconsultoria.com.br
License: GPL
Keywords: web zope plone theme skin simples_consultoria plone3 brasil apyb
Platform: UNKNOWN
Classifier: Framework :: Plone
Classifier: Framework :: Zope2
Classifier: Framework :: Zope3
Classifier: Programming Language :: Python
Classifier: Topic :: Software Development :: Libraries :: Python Modules
